[
  {"member_id": "D001", "name": "テスト 太郎",   "birthday": "08-20", "married_on": null,    "spouse_name": null,         "married_on_private": false},
  {"member_id": "D002", "name": "ダミー 花子",   "birthday": "08-21", "married_on": "11-29", "spouse_name": "ダミー 一郎", "married_on_private": false},
  {"member_id": "D003", "name": "サンプル 次郎", "birthday": "08-23", "married_on": null,    "spouse_name": null,         "married_on_private": false},
  {"member_id": "D004", "name": "架空 三郎",     "birthday": "08-26", "married_on": "05-05", "spouse_name": "架空 良子",   "married_on_private": false},
  {"member_id": "D005", "name": "デモ 四郎",     "birthday": "08-26", "married_on": null,    "spouse_name": null,         "married_on_private": false},
  {"member_id": "D006", "name": "テスト 五郎",   "birthday": "12-01", "married_on": null,    "spouse_name": null,         "married_on_private": false},
  {"member_id": "D007", "name": "ダミー 六郎",   "birthday": "04-15", "married_on": "04-20", "spouse_name": "ダミー 桜子", "married_on_private": false},
  {"member_id": "D008", "name": "サンプル 七子", "birthday": "08-22", "married_on": null,    "spouse_name": null,         "married_on_private": false},
  {"member_id": "D009", "name": "架空 八郎",     "birthday": "08-19", "married_on": "11-30", "spouse_name": "架空 八子",   "married_on_private": false},
  {"member_id": "D010", "name": "デモ 九子",     "birthday": "10-10", "married_on": null,    "spouse_name": null,         "married_on_private": false},
  {"member_id": "D011", "name": "架空 十郎",     "birthday": null,    "married_on": "08-20", "spouse_name": "架空 十子",   "married_on_private": true}
]
